{"cameraMode":{"drawMode":0,"name":"Shaded","section":"Shading Mode"},"sceneLighting":false,"audioPlay":false,"sceneViewState":{"m_AlwaysRefresh":false,"showFog":true,"showSkybox":false,"showFlares":true,"showImageEffects":true,"showParticleSystems":true,"showVisualEffectGraphs":true,"m_FxEnabled":true},"in2DMode":false,"pivot":{"x":0.9194183349609375,"y":1.4715864658355713,"z":6.918789386749268},"rotation":{"x":-0.1270216852426529,"y":0.8728582262992859,"z":-0.34087073802948,"w":-0.3252607583999634},"size":1.9113332033157349,"orthographic":false}