{"cameraMode":{"drawMode":0,"name":"Shaded","section":"Shading Mode"},"sceneLighting":false,"audioPlay":false,"sceneViewState":{"m_AlwaysRefresh":false,"showFog":true,"showSkybox":false,"showFlares":true,"showImageEffects":true,"showParticleSystems":true,"showVisualEffectGraphs":true,"m_FxEnabled":true},"in2DMode":false,"pivot":{"x":-0.7735810279846191,"y":1.706317663192749,"z":1.1005172729492188},"rotation":{"x":0.14929720759391786,"y":-0.8359694480895996,"z":0.27796047925949099,"w":0.4490136206150055},"size":2.466646194458008,"orthographic":false}